UnitPie/FunctionTesting.py
UnitPie/SubClassManagement.py
UnitPie/__init__.py
UnitPie/__main__.py
UnitPie/data.py
UnitPie-1.0.0.2.dist-info/METADATA
UnitPie-1.0.0.2.dist-info/WHEEL
UnitPie-1.0.0.2.dist-info/license.txt
UnitPie-1.0.0.2.dist-info/top_level.txt
UnitPie-1.0.0.2.dist-info/RECORD
