Metadata-Version: 2.1
Name: UnitPie
Version: 1.0.0.2
Summary: Tired of these testing libraries such as pytest and unittest? UnitPie is here to change that!
Author: Sandu Bogdan
Author-email: bogdanelsandu@hotmail.com
Classifier: Programming Language :: Python :: 3
Classifier: License :: OSI Approved :: MIT License
Classifier: Operating System :: OS Independent
Requires-Python: >=3.9
License-File: license.txt
